sqlthought/__init__.py
sqlthought/cli.py
sqlthought/config.py
sqlthought/llm.py
sqlthought/nlq/__init__.py
sqlthought/nlq/build_graph.py
sqlthought/nlq/conversion.py
sqlthought/nlq/nodes.py
sqlthought/nlq/state.py
sqlthought/utils/db_utils.py
sqlthought/utils/error_taxonomy.py
sqlthought/utils/logger.py
sqlthought/utils/visualizer.py
sqlthought-0.0.1.dist-info/licenses/LICENSE
sqlthought-0.0.1.dist-info/METADATA
sqlthought-0.0.1.dist-info/WHEEL
sqlthought-0.0.1.dist-info/entry_points.txt
sqlthought-0.0.1.dist-info/top_level.txt
sqlthought-0.0.1.dist-info/RECORD
