Metadata-Version: 2.4
Name: sqlthought
Version: 0.0.1
Summary: A multi-agent SQL-of-Thought engine for NLQ-to-SQL, correction loops, and evaluation.
Author-email: Tiyasa Mukherjee <mukherjeetiyasa1998@gmail.com>
License-Expression: MIT
Keywords: nlq,sql,text-to-sql,langgraph,llm,agentic-ai
Requires-Python: >=3.9
License-File: LICENSE
Requires-Dist: langgraph>=0.3.3
Requires-Dist: sqlparse
Requires-Dist: pydantic>=2.0
Requires-Dist: psutil
Requires-Dist: Pillow
Requires-Dist: langchain-ollama
Requires-Dist: deepeval
Requires-Dist: groq>=0.5.0
Dynamic: license-file
